neurst/__init__.py
neurst/__version__.py
neurst/cli/__init__.py
neurst/cli/audio_tfrecord_analysis.py
neurst/cli/avg_checkpoint.py
neurst/cli/cascade_st.py
neurst/cli/convert_checkpoint.py
neurst/cli/create_tfrecords.py
neurst/cli/extract_audio_transcripts.py
neurst/cli/generate_vocab.py
neurst/cli/inspect_checkpoint.py
neurst/cli/run_exp.py
neurst/cli/text_metric.py
neurst/cli/view_registry.py
neurst/cli/view_tfrecord.py
neurst/criterions/__init__.py
neurst/criterions/criterion.py
neurst/criterions/joint_criterion.py
neurst/criterions/label_smoothed_cross_entropy.py
neurst/data/__init__.py
neurst/data/dataset_utils.py
neurst/data/audio/__init__.py
neurst/data/audio/feature_extractor.py
neurst/data/audio/float_identity.py
neurst/data/audio/log_mel_fbank.py
neurst/data/data_pipelines/__init__.py
neurst/data/data_pipelines/bert_data_pipeline.py
neurst/data/data_pipelines/data_pipeline.py
neurst/data/data_pipelines/gpt2_data_pipeline.py
neurst/data/data_pipelines/multilingual_text_data_pipeline.py
neurst/data/data_pipelines/text_data_pipeline.py
neurst/data/data_pipelines/transcript_data_pipeline.py
neurst/data/datasets/__init__.py
neurst/data/datasets/dataset.py
neurst/data/datasets/mixed_train_dataset.py
neurst/data/datasets/multilingual_translation_dataset.py
neurst/data/datasets/multiple_dataset.py
neurst/data/datasets/parallel_text_dataset.py
neurst/data/datasets/text_gen_dataset.py
neurst/data/datasets/audio/__init__.py
neurst/data/datasets/audio/audio_dataset.py
neurst/data/datasets/audio/aug_librispeech.py
neurst/data/datasets/audio/common_voice.py
neurst/data/datasets/audio/iwslt.py
neurst/data/datasets/audio/librispeech.py
neurst/data/datasets/audio/mustc.py
neurst/data/datasets/audio/tedlium.py
neurst/data/datasets/data_sampler/__init__.py
neurst/data/datasets/data_sampler/data_sampler.py
neurst/data/datasets/data_sampler/temperature_sampler.py
neurst/data/text/__init__.py
neurst/data/text/bpe.py
neurst/data/text/character.py
neurst-0.1.1.dist-info/LICENSE
neurst-0.1.1.dist-info/METADATA
neurst-0.1.1.dist-info/WHEEL
neurst-0.1.1.dist-info/entry_points.txt
neurst-0.1.1.dist-info/top_level.txt
neurst-0.1.1.dist-info/RECORD
