Metadata-Version: 2.1
Name: neurst
Version: 0.1.1
Summary: Neural Speech Translation Toolkit
Home-page: https://github.com/bytedance/neurst
Author: ZhaoChengqi
Author-email: zhaochengqi.d@bytedance.com
License: UNKNOWN
Keywords: neurst
Platform: UNKNOWN
Classifier: Intended Audience :: Developers
Classifier: Programming Language :: Python :: 3.6
Classifier: Programming Language :: Python :: 3.7
Classifier: Programming Language :: Python :: 3.8
Requires-Python: >=3.6
Requires-Dist: six (<2.0.0,>=1.11.0)
Requires-Dist: pyyaml (>=3.13)
Requires-Dist: sacrebleu (>=1.4.0)
Requires-Dist: regex (>=2019.1.24)
Requires-Dist: sacremoses (>=0.0.38)
Requires-Dist: tqdm (>=0.46)
Provides-Extra: dev
Requires-Dist: flake8 (<4.0.0,>=3.5.0) ; extra == 'dev'
Requires-Dist: tox (<4.0.0,>=3.0.0) ; extra == 'dev'
Requires-Dist: isort (<5.0.0,>=4.0.0) ; extra == 'dev'
Requires-Dist: pytest (<5.0.0,>=4.0.0) ; extra == 'dev'
Requires-Dist: six (<2.0.0,>=1.11.0) ; extra == 'dev'
Requires-Dist: pyyaml (>=3.13) ; extra == 'dev'
Requires-Dist: sacrebleu (>=1.4.0) ; extra == 'dev'
Requires-Dist: regex (>=2019.1.24) ; extra == 'dev'
Requires-Dist: sacremoses (>=0.0.38) ; extra == 'dev'
Requires-Dist: tqdm (>=0.46) ; extra == 'dev'
Requires-Dist: jieba (>=0.42.1) ; extra == 'dev'
Requires-Dist: subword-nmt (>=0.3.7) ; extra == 'dev'
Requires-Dist: thai-segmenter (>=0.4.1) ; extra == 'dev'
Requires-Dist: soundfile (>=0.10) ; extra == 'dev'
Requires-Dist: python-speech-features (>=0.6) ; extra == 'dev'
Requires-Dist: transformers (>=3.4.0) ; extra == 'dev'
Requires-Dist: sentencepiece (>=0.1.7) ; extra == 'dev'
Requires-Dist: mecab-python3 (>=1.0.3) ; extra == 'dev'
Requires-Dist: ipadic (>=1.0.0) ; extra == 'dev'
Requires-Dist: torch (>=1.7.0) ; extra == 'dev'
Requires-Dist: fairseq (>=0.10.1) ; extra == 'dev'
Requires-Dist: tensorflow-addons (>=0.11.2) ; extra == 'dev'
Requires-Dist: pydub (>=0.24.1) ; extra == 'dev'
Requires-Dist: mypy (>=0.620) ; (python_version >= "3.6") and extra == 'dev'
